migrations/__init__.py
yagnesh_demo-0.0.1.dist-info/LICENSE
yagnesh_demo-0.0.1.dist-info/METADATA
yagnesh_demo-0.0.1.dist-info/WHEEL
yagnesh_demo-0.0.1.dist-info/top_level.txt
yagnesh_demo-0.0.1.dist-info/RECORD
